bornrule/__init__.py
bornrule/born.py
bornrule/sql/__init__.py
bornrule/sql/born.py
bornrule/sql/database.py
bornrule/sql/mysql.py
bornrule/sql/postgresql.py
bornrule/sql/schema.py
bornrule/sql/sqlite.py
bornrule/torch/__init__.py
bornrule/torch/born.py
bornrule-0.3.2.dist-info/LICENSE
bornrule-0.3.2.dist-info/METADATA
bornrule-0.3.2.dist-info/WHEEL
bornrule-0.3.2.dist-info/RECORD
