Metadata-Version: 2.3
Name: bornrule
Version: 0.3.2
Summary: Implements the Born Classifier
License: MIT
Author: Emanuele Guidotti
Author-email: emanuele.guidotti@usi.ch
Requires-Python: >=3.6.1
Classifier: License :: OSI Approved :: MIT License
Classifier: Programming Language :: Python :: 3
Classifier: Programming Language :: Python :: 3.7
Classifier: Programming Language :: Python :: 3.8
Classifier: Programming Language :: Python :: 3.9
Classifier: Programming Language :: Python :: 3.10
Classifier: Programming Language :: Python :: 3.11
Classifier: Programming Language :: Python :: 3.12
Classifier: Programming Language :: Python :: 3.13
Requires-Dist: numpy (>=1.19.5)
Requires-Dist: pandas (>=1.1.5)
Requires-Dist: scikit-learn (>=0.24.2)
Requires-Dist: scipy (>=1.5.4)
Project-URL: Documentation, https://bornrule.eguidotti.com
Project-URL: Repository, https://github.com/eguidotti/bornrule
